setup.py
mess_server_skif.egg-info/PKG-INFO
mess_server_skif.egg-info/SOURCES.txt
mess_server_skif.egg-info/dependency_links.txt
mess_server_skif.egg-info/requires.txt
mess_server_skif.egg-info/top_level.txt
server/__init__.py
server/server.py
server/common/__init__.py
server/common/decorators.py
server/common/descriptors.py
server/common/errors.py
server/common/metaclasses.py
server/common/utils.py
server/common/variables.py
server/log/__init__.py
server/log/client_log_config.py
server/log/server_log_config.py
server/server/__init__.py
server/server/add_user.py
server/server/config_window.py
server/server/core.py
server/server/main_window.py
server/server/remove_user.py
server/server/server_database.py
server/server/stat_window.py
server/unit_test/__init__.py
server/unit_test/test_client.py
server/unit_test/test_server.py
server/unit_test/test_utils.py