Metadata-Version: 1.0
Name: mess-server-skif
Version: 0.0.1
Summary: Messenger_Server
Home-page: UNKNOWN
Author: Egorov Viktor
Author-email: seal_skif@mail.ru
License: UNKNOWN
Platform: UNKNOWN
